evilunit/__init__.py
evilunit/_import.py
evilunit/nestedtest.py
evilunit/parameterized.py
evilunit/shortcuts.py
evilunit/tests/__init__.py
evilunit/tests/test_frame.py
evilunit/tests/test_it_nested_test.py
evilunit/tests/test_nested.py
evilunit/tests/test_paramaterized.py
evilunit/tests/test_parts.py
evilunit-0.2.1.dist-info/LICENSE
evilunit-0.2.1.dist-info/METADATA
evilunit-0.2.1.dist-info/WHEEL
evilunit-0.2.1.dist-info/entry_points.txt
evilunit-0.2.1.dist-info/top_level.txt
evilunit-0.2.1.dist-info/RECORD
