Metadata-Version: 2.1
Name: evilunit
Version: 0.2.1
Summary: evil parts of unittest
Home-page: https://github.com/podhmo/evilunit
Author: podhmo
Author-email: 
License: UNKNOWN
Keywords: unittest,test
Platform: UNKNOWN
Classifier: Programming Language :: Python
Classifier: Intended Audience :: Developers
Classifier: Topic :: Software Development :: Libraries :: Python Modules
Classifier: License :: OSI Approved :: MIT License
Classifier: Operating System :: OS Independent
Classifier: Programming Language :: Python :: 3
Classifier: Programming Language :: Python :: 3.6
Classifier: Programming Language :: Python :: 3.7
Classifier: Programming Language :: Python :: 3.8
Provides-Extra: docs
Provides-Extra: testing
Requires-Dist: pytest ; extra == 'testing'
Requires-Dist: flake8 ; extra == 'testing'
Requires-Dist: black ; extra == 'testing'
